amazon_scrape-1.0.9.dist-info/licenses/LICENSE
amazon_scraper/__init__.py
amazon_scraper/scraper.py
amazon_scraper/version.py
amazon_scrape-1.0.9.dist-info/METADATA
amazon_scrape-1.0.9.dist-info/WHEEL
amazon_scrape-1.0.9.dist-info/entry_points.txt
amazon_scrape-1.0.9.dist-info/top_level.txt
amazon_scrape-1.0.9.dist-info/RECORD
