Metadata-Version: 2.4
Name: amazon_scrape
Version: 1.0.9
Summary: Scrape Amazon product data such as Product Name, Product Images, Number of Reviews, Price, Product URL, and ASIN.
Home-page: https://finbarrs.eu
Author: Finbarrs Oketunji
Author-email: f@finbarrs.eu
License: MIT
Project-URL: Bug Tracker, https://github.com/0xnu/amazonproducts/issues
Project-URL: Changes, https://github.com/0xnu/amazonproducts/blob/main/CHANGELOG.md
Project-URL: Documentation, https://github.com/0xnu/amazonproducts/blob/main/README.md
Project-URL: Source Code, https://github.com/0xnu/amazonproducts
Keywords: amazon,products,ecommerce,price,reviews,ratings
Classifier: Development Status :: 5 - Production/Stable
Classifier: Intended Audience :: Developers
Classifier: License :: OSI Approved :: MIT License
Classifier: Operating System :: OS Independent
Classifier: Programming Language :: Python
Classifier: Programming Language :: Python :: 2
Classifier: Programming Language :: Python :: 2.7
Classifier: Programming Language :: Python :: 3
Classifier: Programming Language :: Python :: 3.4
Classifier: Programming Language :: Python :: 3.5
Classifier: Programming Language :: Python :: 3.6
Classifier: Programming Language :: Python :: 3.7
Classifier: Programming Language :: Python :: 3.8
Classifier: Programming Language :: Python :: 3.9
Classifier: Programming Language :: Python :: 3.10
Classifier: Programming Language :: Python :: 3.11
Classifier: Programming Language :: Python :: Implementation :: PyPy
Classifier: Topic :: Software Development :: Libraries :: Python Modules
Requires-Python: >=2.7, !=3.0.*, !=3.1.*, !=3.2.*, !=3.3.*
License-File: LICENSE
Requires-Dist: beautifulsoup4
Requires-Dist: requests
Dynamic: author
Dynamic: author-email
Dynamic: classifier
Dynamic: description
Dynamic: description-content-type
Dynamic: home-page
Dynamic: keywords
Dynamic: license
Dynamic: license-file
Dynamic: project-url
Dynamic: requires-dist
Dynamic: requires-python
Dynamic: summary
